{
  "movies": [
    {
      "id": 1,
      "title": "The Shawshank Redemption",
      "imgUrl": "https://resizing.flixster.com/nMPTDzWsB7Z44LSCJFlAzB7LuMY=/300x300/v2/https://flxt.tmsimg.com/assets/p15987_k_h9_ac.jpg",
      "productionYear": 1994,
      "numberOfRatings": 1500,
      "sumOfRatings": 7500,
      "description": "Two imprisoned men bond over a number of years, finding solace and eventual redemption through acts of common decency.",
      "trailerUrl": "https://youtube.com/embed/6hB3S9bIaco",
      "actors": [
        "Morgan Freeman",
        "Tim Robins",
        "Clancy Brown",
        "Bob Gunton",
        "William Sadler"
      ],
      "categories": ["drama", "crime"],
      "views": 2137
    },
    {
      "id": 2,
      "title": "The Godfather",
      "imgUrl": "https://resizing.flixster.com/qiPYM9adO26zqlQkX63TE55s8ZE=/300x300/v2/https://flxt.tmsimg.com/assets/p22069_p_v13_ah.jpg",
      "productionYear": 1972,
      "numberOfRatings": 2000,
      "sumOfRatings": 9000,
      "description": "The aging patriarch of an organized crime dynasty transfers control of his clandestine empire to his reluctant son.",
      "trailerUrl": "https://youtube.com/embed/sY1S34973zA",
      "actors": [
        "Marlon Brando",
        "Al Pacino",
        "James Caan",
        "Robert Duvall",
        "Diane Keaton"
      ],
      "categories": ["crime", "drama"],
      "views": 3124
    },
    {
      "id": 2,
      "title": "Inception",
      "imgUrl": "https://resizing.flixster.com/l8Rw8ej7jGOs7LZlOeazZKoAZh0=/300x300/v2/https://flxt.tmsimg.com/assets/p7824498_p_v13_ak.jpg",
      "productionYear": 2010,
      "numberOfRatings": 2000,
      "sumOfRatings": 9200,
      "description": "A thief who steals corporate secrets through the use of dream-sharing technology is given the inverse task of planting an idea into the mind of a C.E.O.",
      "trailerUrl": "https://youtube.com/embed/8hP9D6kZseM",
      "actors": [
        "Leonardo DiCaprio",
        "Joseph Gordon-Levitt",
        "Ellen Page",
        "Tom Hardy",
        "Ken Watanabe"
      ],
      "categories": ["action", "sci-fi"],
      "views": 3789
    },
    {
      "id": 3,
      "title": "The Dark Knight",
      "imgUrl": "https://resizing.flixster.com/7UvphluRwYxO1C5CDiQzdjezmfI=/300x300/v2/https://flxt.tmsimg.com/assets/p161217_p_v13_ab.jpg",
      "productionYear": 2008,
      "numberOfRatings": 2500,
      "sumOfRatings": 9600,
      "description": "When the menace known as the Joker wreaks havoc and chaos on the people of Gotham, Batman must accept one of the greatest psychological and physical tests of his ability to fight injustice.",
      "trailerUrl": "https://youtube.com/embed/EXeTwQWrcwY",
      "actors": [
        "Christian Bale",
        "Heath Ledger",
        "Aaron Eckhart",
        "Michael Caine",
        "Maggie Gyllenhaal"
      ],
      "categories": ["action", "crime"],
      "views": 4521
    },
    {
      "id": 4,
      "title": "Pulp Fiction",
      "imgUrl": "https://resizing.flixster.com/3L7ZzZ7T57kPtXzr-LD-aw5dp2Q=/300x300/v2/https://flxt.tmsimg.com/assets/p19581_p_v10_af.jpg",
      "productionYear": 1994,
      "numberOfRatings": 1800,
      "sumOfRatings": 8800,
      "description": "The lives of two mob hitmen, a boxer, a gangster's wife, and a pair of diner bandits intertwine in four tales of violence and redemption.",
      "trailerUrl": "https://youtube.com/embed/s7EdQ4FqbhY",
      "actors": [
        "John Travolta",
        "Samuel L. Jackson",
        "Uma Thurman",
        "Bruce Willis",
        "Harvey Keitel"
      ],
      "categories": ["crime", "drama"],
      "views": 2956
    },
    {
      "id": 5,
      "title": "The Lord of the Rings: The Fellowship of the Ring",
      "imgUrl": "https://resizing.flixster.com/yGwSyNh6IqHtVMvKT37TpR_GHhA=/300x300/v2/https://flxt.tmsimg.com/assets/p28408_p_v13_aj.jpg",
      "productionYear": 2001,
      "numberOfRatings": 2200,
      "sumOfRatings": 9400,
      "description": "A meek Hobbit from the Shire and eight companions set out on a journey to destroy the powerful One Ring and save Middle-earth from the Dark Lord Sauron.",
      "trailerUrl": "https://youtube.com/embed/V75dMMIW2B4",
      "actors": [
        "Elijah Wood",
        "Ian McKellen",
        "Viggo Mortensen",
        "Sean Astin",
        "Orlando Bloom"
      ],
      "categories": ["adventure", "fantasy"],
      "views": 5178
    },
    {
      "id": 6,
      "title": "The Matrix",
      "imgUrl": "https://resizing.flixster.com/c1ix9CFx8zy3eytJU6iRw0Kxv-w=/300x300/v2/https://flxt.tmsimg.com/assets/p24591_p_v13_af.jpg",
      "productionYear": 1999,
      "numberOfRatings": 2800,
      "sumOfRatings": 9100,
      "description": "A computer hacker learns from mysterious rebels about the true nature of his reality and his role in the war against its controllers.",
      "trailerUrl": "https://youtube.com/embed/vKQi3bBA1y8",
      "actors": [
        "Keanu Reeves",
        "Laurence Fishburne",
        "Carrie-Anne Moss",
        "Hugo Weaving",
        "Joe Pantoliano"
      ],
      "categories": ["action", "sci-fi"],
      "views": 6234
    },
    {
      "id": 7,
      "title": "Fight Club",
      "imgUrl": "https://resizing.flixster.com/KBy1ylftXxzz-n-X5_G4gsUYfls=/300x300/v2/https://flxt.tmsimg.com/assets/p23131_p_v10_aa.jpg",
      "productionYear": 1999,
      "numberOfRatings": 2400,
      "sumOfRatings": 8900,
      "description": "An insomniac office worker and a devil-may-care soapmaker form an underground fight club that evolves into something much, much more.",
      "trailerUrl": "https://youtube.com/embed/qtRKdVHc-cE",
      "actors": [
        "Brad Pitt",
        "Edward Norton",
        "Helena Bonham Carter",
        "Meat Loaf",
        "Jared Leto"
      ],
      "categories": ["drama"],
      "views": 4276
    },
    {
      "id": 8,
      "title": "Forrest Gump",
      "imgUrl": "https://resizing.flixster.com/XpIY0dD22p9SpW68HYsLHLFwvTg=/300x300/v2/https://flxt.tmsimg.com/assets/p79_p_v13_ao.jpg",
      "productionYear": 1994,
      "numberOfRatings": 3100,
      "sumOfRatings": 9600,
      "description": "The presidencies of Kennedy and Johnson, the events of Vietnam, Watergate, and other historical events unfold through the perspective of an Alabama man with an IQ of 75.",
      "trailerUrl": "https://youtube.com/embed/uPIEn0M8su0",
      "actors": [
        "Tom Hanks",
        "Robin Wright",
        "Gary Sinise",
        "Sally Field",
        "Haley Joel Osment"
      ],
      "categories": ["drama", "romance"],
      "views": 5783
    },
    {
      "id": 9,
      "title": "The Avengers",
      "imgUrl": "https://resizing.flixster.com/LoHZVbzeG2ICd8RftSS3ob4Jzoc=/300x300/v2/https://flxt.tmsimg.com/assets/p9188481_p_v13_ak.jpg",
      "productionYear": 2012,
      "numberOfRatings": 2900,
      "sumOfRatings": 9300,
      "description": "Earth's mightiest heroes must come together and learn to fight as a team if they are to stop the mischievous Loki and his alien army from enslaving humanity.",
      "trailerUrl": "https://youtube.com/embed/eOrNdBpGMv8",
      "actors": [
        "Robert Downey Jr.",
        "Chris Evans",
        "Mark Ruffalo",
        "Chris Hemsworth",
        "Scarlett Johansson"
      ],
      "categories": ["action", "adventure"],
      "views": 6391
    },
    {
      "id": 10,
      "title": "The Godfather",
      "imgUrl": "https://resizing.flixster.com/9TyLE6eWTRI_M7MszCwRDm6zVI0=/300x300/v2/https://flxt.tmsimg.com/assets/p22083_p_v10_aa.jpg",
      "productionYear": 1972,
      "numberOfRatings": 2700,
      "sumOfRatings": 9700,
      "description": "The aging patriarch of an organized crime dynasty transfers control of his clandestine empire to his reluctant son.",
      "trailerUrl": "https://youtube.com/embed/sY1S34973zA",
      "actors": [
        "Marlon Brando",
        "Al Pacino",
        "James Caan",
        "Robert Duvall",
        "Diane Keaton"
      ],
      "categories": ["crime", "drama"],
      "views": 5214
    },
    {
      "id": 11,
      "title": "Interstellar",
      "imgUrl": "https://resizing.flixster.com/F3m_JsrIlByAy5ytCZ-y_NzVUMg=/300x300/v2/https://flxt.tmsimg.com/assets/p10216908_p_v13_ah.jpg",
      "productionYear": 2014,
      "numberOfRatings": 3200,
      "sumOfRatings": 9400,
      "description": "A team of explorers undertakes a mission to save humanity by traveling through a wormhole in search of a new habitable planet.",
      "trailerUrl": "https://youtube.com/embed/zSWdZVtXT7E",
      "actors": [
        "Matthew McConaughey",
        "Anne Hathaway",
        "Jessica Chastain",
        "Michael Caine",
        "Mackenzie Foy"
      ],
      "categories": ["adventure", "sci-fi"],
      "views": 4925
    },
    {
      "id": 12,
      "title": "The Lion King",
      "imgUrl": "https://resizing.flixster.com/4ZXJ7d1bZiILcHg3CDgGBXN_3po=/300x300/v2/https://flxt.tmsimg.com/assets/p8617_p_v8_aa.jpg",
      "productionYear": 1994,
      "numberOfRatings": 3500,
      "sumOfRatings": 9800,
      "description": "A lion prince flees his kingdom after the murder of his father and learns the true meaning of responsibility and bravery.",
      "trailerUrl": "https://youtube.com/embed/4sj1MT05lAA",
      "actors": [
        "Matthew Broderick",
        "Jeremy Irons",
        "James Earl Jones",
        "Nathan Lane",
        "Moira Kelly"
      ],
      "categories": ["animation", "adventure"],
      "views": 5763
    },
    {
      "id": 13,
      "title": "The Dark Knight Rises",
      "imgUrl": "https://resizing.flixster.com/0eFK7tKEHEemJmVVlqieQ0qVQ8M=/300x300/v2/https://flxt.tmsimg.com/assets/p8947398_p_v10_aa.jpg",
      "productionYear": 2012,
      "numberOfRatings": 3100,
      "sumOfRatings": 9200,
      "description": "Eight years after the Joker's reign of anarchy, Batman, with the help of the enigmatic Catwoman, is forced from his exile to save Gotham City from the brutal guerrilla terrorist Bane.",
      "trailerUrl": "https://youtube.com/embed/g8evyE9TuYk",
      "actors": [
        "Christian Bale",
        "Tom Hardy",
        "Anne Hathaway",
        "Gary Oldman",
        "Michael Caine"
      ],
      "categories": ["action", "thriller"],
      "views": 4351
    },
    {
      "id": 14,
      "title": "The Shawshank Redemption",
      "imgUrl": "https://resizing.flixster.com/nMPTDzWsB7Z44LSCJFlAzB7LuMY=/300x300/v2/https://flxt.tmsimg.com/assets/p15987_k_h9_ac.jpg",
      "productionYear": 1994,
      "numberOfRatings": 1500,
      "sumOfRatings": 7500,
      "description": "Two imprisoned men bond over a number of years, finding solace and eventual redemption through acts of common decency.",
      "trailerUrl": "https://youtube.com/embed/6hB3S9bIaco",
      "actors": [
        "Morgan Freeman",
        "Tim Robins",
        "Clancy Brown",
        "Bob Gunton",
        "William Sadler"
      ],
      "categories": ["drama", "crime"],
      "views": 2137
    },
    {
      "id": 15,
      "title": "Pulp Fiction",
      "imgUrl": "https://resizing.flixster.com/ygMoZdcQDEx2CgSpWzNv1ClE6Do=/300x300/v2/https://flxt.tmsimg.com/assets/p19581_p_v10_af.jpg",
      "productionYear": 1994,
      "numberOfRatings": 1800,
      "sumOfRatings": 8800,
      "description": "The lives of two mob hitmen, a boxer, a gangster's wife, and a pair of diner bandits intertwine in four tales of violence and redemption.",
      "trailerUrl": "https://youtube.com/embed/s7EdQ4FqbhY",
      "actors": [
        "John Travolta",
        "Samuel L. Jackson",
        "Uma Thurman",
        "Bruce Willis",
        "Harvey Keitel"
      ],
      "categories": ["crime", "drama"],
      "views": 2956
    },
    {
      "id": 16,
      "title": "Inception",
      "imgUrl": "https://resizing.flixster.com/zvu6nYO7nQHhrCjCp5SyS2WPhkI=/300x300/v2/https://flxt.tmsimg.com/assets/p7922417_p_v13_af.jpg",
      "productionYear": 2010,
      "numberOfRatings": 3700,
      "sumOfRatings": 9500,
      "description": "A thief with the ability to enter people's dreams is given the task of planting an idea into the mind of a CEO.",
      "trailerUrl": "https://youtube.com/embed/YoHD9XEInc0",
      "actors": [
        "Leonardo DiCaprio",
        "Joseph Gordon-Levitt",
        "Ellen Page",
        "Tom Hardy",
        "Ken Watanabe"
      ],
      "categories": ["action", "sci-fi"],
      "views": 5243
    },
    {
      "id": 17,
      "title": "The Silence of the Lambs",
      "imgUrl": "https://resizing.flixster.com/fk9uTYGQsRmXyLpTF-Ut-3v62t0=/300x300/v2/https://flxt.tmsimg.com/assets/p15606_p_v13_aa.jpg",
      "productionYear": 1991,
      "numberOfRatings": 3000,
      "sumOfRatings": 9200,
      "description": "A young FBI cadet must confide in an incarcerated and manipulative killer to receive his help on catching another serial killer.",
      "trailerUrl": "https://youtube.com/embed/W6Mm8Sbe__o",
      "actors": [
        "Jodie Foster",
        "Anthony Hopkins",
        "Scott Glenn",
        "Ted Levine",
        "Anthony Heald"
      ],
      "categories": ["crime", "thriller"],
      "views": 4265
    },
    {
      "id": 18,
      "title": "The Departed",
      "imgUrl": "https://resizing.flixster.com/fQlE8l0VdnnkYBfzBrx8MsMn-vg=/300x300/v2/https://flxt.tmsimg.com/assets/p55908_p_v13_aa.jpg",
      "productionYear": 2006,
      "numberOfRatings": 3400,
      "sumOfRatings": 9700,
      "description": "An undercover cop and a mole in the police attempt to identify each other while infiltrating an Irish gang in South Boston.",
      "trailerUrl": "https://youtube.com/embed/SGWvwjZ0eDc",
      "actors": [
        "Leonardo DiCaprio",
        "Matt Damon",
        "Jack Nicholson",
        "Mark Wahlberg",
        "Martin Sheen"
      ],
      "categories": ["crime", "drama"],
      "views": 5872
    },
    {
      "id": 19,
      "title": "The Prestige",
      "imgUrl": "https://resizing.flixster.com/QdJrjtlx2v8eMnsCsnVjNcHhfOU=/300x300/v2/https://flxt.tmsimg.com/assets/p58953_p_v10_ac.jpg",
      "productionYear": 2006,
      "numberOfRatings": 3300,
      "sumOfRatings": 9500,
      "description": "After a tragic accident, two stage magicians engage in a battle to create the ultimate illusion while sacrificing everything they have to outwit each other.",
      "trailerUrl": "https://youtube.com/embed/ijXruSzfGEc",
      "actors": [
        "Hugh Jackman",
        "Christian Bale",
        "Michael Caine",
        "Scarlett Johansson",
        "Rebecca Hall"
      ],
      "categories": ["drama", "mystery"],
      "views": 3967
    },
    {
      "id": 20,
      "title": "The Matrix",
      "imgUrl": "https://resizing.flixster.com/OXqQqOKrytZSpQQOQ9dHwec7nYE=/300x300/v2/https://flxt.tmsimg.com/assets/p20141_p_v10_ab.jpg",
      "productionYear": 1999,
      "numberOfRatings": 3800,
      "sumOfRatings": 9100,
      "description": "A computer hacker learns from mysterious rebels about the true nature of his reality and his role in the war against its controllers.",
      "trailerUrl": "https://youtube.com/embed/vKQi3bBA1y8",
      "actors": [
        "Keanu Reeves",
        "Laurence Fishburne",
        "Carrie-Anne Moss",
        "Hugo Weaving",
        "Joe Pantoliano"
      ],
      "categories": ["action", "sci-fi"],
      "views": 6123
    }
  ],
  "users": [
    {
      "email": "user@user.com",
      "password": "user123",
      "username": "user"
    }
  ]
}
